LICENSE
MANIFEST.in
README.md
setup.py
django_verbatim/__init__.py
django_verbatim/models.py
django_verbatim.egg-info/PKG-INFO
django_verbatim.egg-info/SOURCES.txt
django_verbatim.egg-info/dependency_links.txt
django_verbatim.egg-info/top_level.txt
django_verbatim/templatetags/__init__.py
django_verbatim/templatetags/verbatim.py