Metadata-Version: 1.1
Name: django-verbatim
Version: 0.1
Summary: Django template block tag which renders template syntax characters within the block as normal text.
Home-page: https://github.com/aljosa/django-verbatim
Author: Aljosa Mohorovic
Author-email: aljosa.mohorovic@gmail.com
License: MIT License
Keywords: django template tag verbatim
Platform: any
Classifier: Development Status :: 2 - Pre-Alpha
Classifier: Environment :: Web Environment
Classifier: Framework :: Django
Classifier: Intended Audience :: Developers
Classifier: License :: OSI Approved :: MIT License
Classifier: Operating System :: OS Independent
Classifier: Programming Language :: Python
Classifier: Topic :: Software Development :: Libraries :: Application Frameworks
Classifier: Topic :: Software Development :: Libraries :: Python Modules
